fairspec/__init__.py
fairspec-0.1.0.dist-info/METADATA
fairspec-0.1.0.dist-info/WHEEL
fairspec-0.1.0.dist-info/RECORD
