Metadata-Version: 2.4
Name: fairspec
Version: 0.1.0
Summary: Fairspec Python
Project-URL: homepage, https://github.com/datisthq/fairspec
Project-URL: repository, https://github.com/datisthq/fairspec
Author: Evgeny Karev
License-Expression: MIT
Classifier: Programming Language :: Python :: 3
Classifier: Programming Language :: Python :: 3.12
Classifier: Topic :: Software Development :: Libraries :: Python Modules
Requires-Python: >=3.12
